MANIFEST.in
README.md
setup.py
dash_large_upload_component/Upload.py
dash_large_upload_component/__init__.py
dash_large_upload_component/_imports_.py
dash_large_upload_component/dash_large_upload_component.dev.js
dash_large_upload_component/dash_large_upload_component.min.js
dash_large_upload_component/metadata.json
dash_large_upload_component/package.json
dash_large_upload_component.egg-info/PKG-INFO
dash_large_upload_component.egg-info/SOURCES.txt
dash_large_upload_component.egg-info/dependency_links.txt
dash_large_upload_component.egg-info/top_level.txt