Metadata-Version: 1.0
Name: dash-large-upload-component
Version: 0.0.4
Summary: Resumable.js for uploading large files in Dash
Home-page: UNKNOWN
Author: Dawid Kopczyk <dawid.kopczyk@quantee.ai>
Author-email: UNKNOWN
License: MIT
Platform: UNKNOWN
